[
  {
    "userId": "user-id",
    "name": "The User",
    "avatar": "https://api.adorable.io/avatars/255/the-user@email.png",
    "content": "This is it",
    "createdAt": 1599189961353,
    "id": "YMKG4_GYuYbBgiOZ2nFHZto83Qjs1f"
  },
  {
    "userId": "user-id",
    "name": "The User",
    "avatar": "https://api.adorable.io/avatars/255/the-user@email.png",
    "content": "This is it",
    "createdAt": 1599189980090,
    "id": "MoDf-Zyu-9Ayjkvss3dPxJgg7BUekz"
  },
  {
    "userId": "user-id",
    "name": "The User",
    "avatar": "https://api.adorable.io/avatars/255/the-user@email.png",
    "content": "This is it",
    "createdAt": 1599189983496,
    "id": "5RprImhvl-n89PpXlLKo7TjBMduDrR"
  },
  {
    "userId": "github-737307",
    "name": null,
    "avatar": "https://avatars3.githubusercontent.com/u/737307?v=4",
    "content": "This is the comment content",
    "createdAt": 1599190287292,
    "id": "ZOuy4_TggaEqLHp-9GNutwu_wKgZ19"
  },
  {
    "userId": "github-737307",
    "name": null,
    "avatar": "https://avatars3.githubusercontent.com/u/737307?v=4",
    "content": "This is the comment content",
    "createdAt": 1599190453819,
    "id": "WzzDsbRYiC1n0RiRPD6uVfgLWIohdP"
  }
]